scrapy_colorful_log/__init__.py
scrapy_colorful_log/default_format.py
scrapy_colorful_log/formatter.py
scrapy_colorful_log/utils.py
scrapy_colorful_log-0.0.1.dist-info/licenses/LICENSE
scrapy_colorful_log-0.0.1.dist-info/METADATA
scrapy_colorful_log-0.0.1.dist-info/WHEEL
scrapy_colorful_log-0.0.1.dist-info/top_level.txt
scrapy_colorful_log-0.0.1.dist-info/RECORD
