Metadata-Version: 2.4
Name: scrapy-colorful-log
Version: 0.0.1
Summary: A lightweight scrapy log customize module
Home-page: https://github.com/Manjusaka-N/scrapy-colorful-log.git
Author: Nan
Author-email: 
License: Apache
Classifier: License :: OSI Approved :: Apache Software License
Classifier: Natural Language :: English
Classifier: Operating System :: OS Independent
Classifier: Programming Language :: Python
Classifier: Programming Language :: Python :: 3.6
Classifier: Topic :: Software Development :: Libraries :: Python Modules
Requires-Python: >=3.6
License-File: LICENSE
Dynamic: author
Dynamic: classifier
Dynamic: description
Dynamic: description-content-type
Dynamic: home-page
Dynamic: license
Dynamic: license-file
Dynamic: requires-python
Dynamic: summary
